LICENSE.txt
README.md
setup.py
minourocketpyx/__init__.py
minourocketpyx/rocket.py
minourocketpyx.egg-info/PKG-INFO
minourocketpyx.egg-info/SOURCES.txt
minourocketpyx.egg-info/dependency_links.txt
minourocketpyx.egg-info/requires.txt
minourocketpyx.egg-info/top_level.txt